gen_aws_federated_signin_url/__init__.py
gen_aws_federated_signin_url/_version.py
gen_aws_federated_signin_url/gen_aws_federated_signin_url.py
gen_aws_federated_signin_url-0.1.1.dist-info/LICENSE.txt
gen_aws_federated_signin_url-0.1.1.dist-info/METADATA
gen_aws_federated_signin_url-0.1.1.dist-info/WHEEL
gen_aws_federated_signin_url-0.1.1.dist-info/top_level.txt
gen_aws_federated_signin_url-0.1.1.dist-info/RECORD
