Metadata-Version: 2.1
Name: gen-aws-federated-signin-url
Version: 0.1.1
Summary: Generate AWS Federated Signin URL
Classifier: Programming Language :: Python :: 3.10
Requires-Python: >=3.10.0
License-File: LICENSE.txt
Requires-Dist: boto3 (>=1.26.152)
Requires-Dist: requests (>=2.31.0)
